FPGA4Fun/lcd_text/display.v
module display
#(
    parameter DELAY_FRAMES = 100 //65000 // 27,000,000 (27Mhz) / 115200 Baud rate
)
(
	input clk,
	input ready,
	input [7:0] msg_byte,
	output reg init_complete,
	output reg disp_ce, //Clock Enable
	output reg disp_rw, //Read/Write
	output reg disp_rs, //Register Select
	output reg[7:0] data
);

reg [1:0] state = 0;
reg sending = 0;


localparam DEV_INIT_WAIT = 0;
localparam DEV_INIT = 1;
localparam DEV_READY = 2;

localparam SETUP_INSTRUCTIONS = 5;


reg [7:0] startupCommands[0:5];

initial begin
	startupCommands[0] = 8'b00110000; //Set 8bit mode, 2line display, 5x8 font
	startupCommands[1] = 8'b00001110; //In, cursor on, no blink
	startupCommands[2] = 8'b00000110; //Entry mode, shift cursor automaticaly
	startupCommands[3] = 8'b00000001; //Clear Display
	startupCommands[4] = 8'b00000010; //Home
end


reg [8:0] curcommand = 0;
reg [15:0] waitcounter = 0;

always @(posedge clk) begin
    case (state)
		DEV_INIT_WAIT: begin
			init_complete <= 0;
			disp_ce <= 0;
			disp_rw <= 1; //0;
			disp_rs <= 0;
			if(waitcounter < DELAY_FRAMES)
				waitcounter <= waitcounter + 1;
			else
				state <= DEV_INIT;
		end
        DEV_INIT: begin
			if (curcommand < SETUP_INSTRUCTIONS) begin
				if (~sending) begin
					data <= startupCommands[curcommand];
					disp_ce <= 1;
					disp_rw <= 0; //1;
					disp_rs <= 0;
					sending <= 1;
					curcommand <= curcommand + 1;
				end
				else begin
					disp_ce <= 0;
					sending <= 0;
				end
			end
			else begin
				init_complete <= 1;
				disp_ce <= 0;
				disp_rw <= 1; //0;
				disp_rs <= 1;
				sending <= 0;
				data <= 8'bZ;
				state <= DEV_READY;
			end
		end
		DEV_READY: begin
			if(ready) begin
				data <= msg_byte;
				disp_ce <= 1;
				disp_rw <= 0; //1;
				disp_rs <= 1;
			end
			else begin
				disp_ce <= 0;
				disp_rw <= 1; //0;
				disp_rs <= 1;
			end
		end
	endcase
end

endmodule

FPGA4Fun/lcd_text/display_tb.v
`include "display.v"

module test();
    reg clk = 0;
    reg ready = 0;
    reg [7:0] message = 8'h00;

    wire complete = 0;
    wire ce; // = 0;
    wire rw; // = 0;
    wire rs; // = 0;
    wire [7:0] tdata;
    
    display #(16'd2) d(
        .clk(clk),
        .ready(ready),
        .msg_byte(message),
        .init_complete(complete),
        .disp_ce(ce),
        .disp_rw(rw),
        .disp_rs(rs),
        .data(tdata)
    );


    always
        #1 clk = ~clk;

    initial begin
        $display("Starting DISPLAY_INIT");
        $monitor("CE %u", ce);
        $monitor("CE %u", rw);
        $monitor("CE %u", rs);
        $monitor("Data %b", tdata);
        #30 message=8'd40;
        #1 ready=1;
        #1 ready=0;

        #1000 $finish;
    end

    initial begin
        $dumpfile("display.vcd");
        $dumpvars(0,test);
    end
endmodule

FPGA4Fun/lcd_text/display.vcd
$date
	Tue Mar 28 23:38:11 2023
$end
$version
	Icarus Verilog
$end
$timescale
	1s
$end
$scope module test $end
$var wire 1 ! complete $end
$var wire 8 " tdata [7:0] $end
$var wire 1 # rw $end
$var wire 1 $ rs $end
$var wire 1 % ce $end
$var reg 1 & clk $end
$var reg 8 ' message [7:0] $end
$var reg 1 ( ready $end
$scope module d $end
$var wire 1 & clk $end
$var wire 8 ) msg_byte [7:0] $end
$var wire 1 ( ready $end
$var reg 9 * curcommand [8:0] $end
$var reg 8 + data [7:0] $end
$var reg 1 % disp_ce $end
$var reg 1 $ disp_rs $end
$var reg 1 # disp_rw $end
$var reg 1 , init_complete $end
$var reg 1 - sending $end
$var reg 2 . state [1:0] $end
$var reg 16 / waitcounter [15:0] $end
$upscope $end
$upscope $end
$enddefinitions $end
#0
$dumpvars
b0 /
b0 .
0-
x,
bx +
b0 *
b0 )
0(
b0 '
0&
x%
x$
x#
bx "
x!
$end
#1
b1 /
0$
1#
0%
0!
0,
1&
#2
0&
#3
b10 /
1&
#4
0&
#5
b1 .
1&
#6
0&
#7
b1 *
1-
0#
1%
b110000 "
b110000 +
1&
#8
0&
#9
0-
0%
1&
#10
0&
#11
b10 *
1-
1%
b1110 "
b1110 +
1&
#12
0&
#13
0-
0%
1&
#14
0&
#15
b11 *
1-
1%
b110 "
b110 +
1&
#16
0&
#17
0-
0%
1&
#18
0&
#19
b100 *
1-
1%
b1 "
b1 +
1&
#20
0&
#21
0-
0%
1&
#22
0&
#23
b101 *
1-
1%
b10 "
b10 +
1&
#24
0&
#25
b10 .
bz "
bz +
0-
1$
1#
0%
x!
1,
1&
#26
0&
#27
1&
#28
0&
#29
1&
#30
0&
b101000 '
b101000 )
#31
0#
1%
b101000 "
b101000 +
1&
1(
#32
0&
0(
#33
1#
0%
1&
